[
  {
    "id": "admin-1",
    "name": "Cornet Jean",
    "age": 40,
    "gender": "homme",
    "bio": "Administrateur de Meetyyou",
    "photo": "https://images.unsplash.com/photo-1472099645785-5658abf4ff4e?w=600",
    "city": "Sambava",
    "country": "Madagascar",
    "email": "jlcornet878@gmail.com",
    "is_online": true,
    "is_verified": true
  },
  {
    "id": "699df333289a9048d92d2af6",
    "name": "Jeanne",
    "first_name": "Jeanne",
    "display_name": "Jeanne_75",
    "age": 37,
    "birth_date": "1989-05-12",
    "gender": "femme",
    "bio": "Passionnée de randonnée et de lecture.",
    "profile_title": "À la recherche d'une belle rencontre",
    "looking_for_partner": "Un homme attentionné et cultivé.",
    "photo": "https://images.unsplash.com/photo-1544005313-94ddf0286df2?w=600",
    "city": "Paris",
    "state": "Île-de-France",
    "country": "France",
    "is_online": true,
    "is_verified": false,
    "body_type": "Mince",
    "ethnicity": "Caucasien(ne)",
    "smoking": "Ne fume pas",
    "drinking": "Boit occasionnellement"
  },
  {
    "id": "699c85343d583f96e93eebcb",
    "name": "Jean",
    "age": 44,
    "gender": "homme",
    "bio": "",
    "photo": "https://base44.app/api/apps/69824e8fb1708fad26dcdc79/files/public/69824e8fb1708fad26dcdc79/7772f2d7e_photo.jpg",
    "city": "Ans",
    "country": "Belgique",
    "is_online": true,
    "is_verified": false,
    "body_type": "Sportif(ve)",
    "ethnicity": "Caucasien(ne)",
    "smoking": "Ne fume pas",
    "drinking": "Ne boit pas"
  },
  {
    "id": "69877ddb5ecffefd739e4e6d",
    "name": "Marc Dubois",
    "age": 28,
    "gender": "homme",
    "bio": "Passionné de voyages et de photographie",
    "photo": "https://images.unsplash.com/photo-1500648767791-00dcc994a43e?w=400",
    "city": "Paris",
    "country": "France",
    "is_online": true,
    "is_verified": false
  },
  {
    "id": "69877ddb5ecffefd739e4e6e",
    "name": "Ahmed Diallo",
    "age": 35,
    "gender": "homme",
    "bio": "Entrepreneur et amateur de cuisine",
    "photo": "https://images.unsplash.com/photo-1507003211169-0a1dd7228f2d?w=400",
    "city": "Dakar",
    "country": "Sénégal",
    "is_online": false,
    "is_verified": false
  },
  {
    "id": "69877ddb5ecffefd739e4e6f",
    "name": "Jean-Pierre Martin",
    "age": 42,
    "gender": "homme",
    "bio": "Médecin et passionné de musique classique",
    "photo": "https://images.unsplash.com/photo-1506794778202-cad84cf45f1d?w=400",
    "city": "Lyon",
    "country": "France",
    "is_online": true,
    "is_verified": false
  },
  {
    "id": "69824f072e693baf9be067d3",
    "name": "Florence",
    "age": 38,
    "gender": "femme",
    "bio": "Femme douce et attentionnée, à la recherche d'une relation sérieuse.",
    "photo": "https://images.unsplash.com/photo-1531746020798-e6953c6e8e04?w=600",
    "city": "Sambava",
    "country": "Madagascar",
    "is_online": false,
    "is_verified": true
  },
  {
    "id": "69824f072e693baf9be067d4",
    "name": "Glory",
    "age": 30,
    "gender": "femme",
    "bio": "Hi, I'm Glory or Helena. I'm tired of looking at everyone, joking here. Looking for something real.",
    "photo": "https://images.unsplash.com/photo-1589156280159-27698a70f29e?w=600",
    "city": "Abuja",
    "country": "Nigeria",
    "is_online": true,
    "is_verified": true
  },
  {
    "id": "69824f072e693baf9be067d5",
    "name": "Rosa",
    "age": 44,
    "gender": "femme",
    "bio": "Looking for a serious relationship with a mature man.",
    "photo": "https://images.unsplash.com/photo-1523824921871-d6f1a15151f1?w=600",
    "city": "Douala",
    "country": "Cameroun",
    "is_online": false,
    "is_verified": true
  },
  {
    "id": "69824f072e693baf9be067d7",
    "name": "Amara",
    "age": 28,
    "gender": "femme",
    "bio": "Passionnée par la musique et les voyages.",
    "photo": "https://images.unsplash.com/photo-1531123897727-8f129e1688ce?w=600",
    "city": "Dakar",
    "country": "Sénégal",
    "is_online": true,
    "is_verified": true
  },
  {
    "id": "69824f072e693baf9be067db",
    "name": "Mariama",
    "age": 29,
    "gender": "femme",
    "bio": "Je suis une femme simple et honnête.",
    "photo": "https://images.unsplash.com/photo-1488426862026-3ee34a7d66df?w=600",
    "city": "Conakry",
    "country": "Guinée",
    "is_online": true,
    "is_verified": false
  }
]
